a2d_diary/__init__.py
a2d_diary/__main__.py
a2d_diary/a2d_diary.spec
a2d_diary/create_diary.py
a2d_diary/encode_diary.py
a2d_diary/marking_server.py
a2d_diary/static_resources_middleware.py
a2d_diary/input/1_diaries_to_create/P01.pdf
a2d_diary/input/1_diaries_to_create/P02.pdf
a2d_diary/input/1_diaries_to_create/P03.pdf
a2d_diary/input/1_diaries_to_create/resources/corner_bl.png
a2d_diary/input/1_diaries_to_create/resources/corner_br.png
a2d_diary/input/1_diaries_to_create/resources/corner_ul.png
a2d_diary/input/1_diaries_to_create/resources/corner_ur.png
a2d_diary/input/1_diaries_to_create/resources/logo1.png
a2d_diary/input/2_template_to_encode/template_gray_scale.tif
a2d_diary/input/3_diaries_to_encode/scannedDiary1.tif
a2d_diary/input/3_diaries_to_encode/scannedDiary2.tif
a2d_diary/output/created_diaries/a5_references/.gitkeep
a2d_diary/output/encoded_diaries/.gitkeep
a2d_diary/output/temporal/.gitkeep
a2d_diary/static/.eslintrc.js
a2d_diary/static/async.min.js
a2d_diary/static/create.html
a2d_diary/static/create.js
a2d_diary/static/dropzone.css
a2d_diary/static/dropzone.js
a2d_diary/static/encode.html
a2d_diary/static/encode.js
a2d_diary/static/fabric.js
a2d_diary/static/general.css
a2d_diary/static/index.html
a2d_diary/static/jquery-3.2.1.js
a2d_diary/static/jquery.csv.js
a2d_diary/static/landingPage.js
a2d_diary/static/loadingoverlay.min.js
a2d_diary/static/noty.css
a2d_diary/static/noty.js
a2d_diary/static/package.json
a2d_diary/static/template.png
a2d_diary/static/w3.css
a2d_diary/static/downloads/.gitkeep
a2d_diary/static/fonts/oxygen-v7-latin-regular.woff
a2d_diary/static/fonts/oxygen-v7-latin-regular.woff2
a2d_diary-0.1.5.dist-info/entry_points.txt
a2d_diary-0.1.5.dist-info/LICENSE
a2d_diary-0.1.5.dist-info/WHEEL
a2d_diary-0.1.5.dist-info/METADATA
a2d_diary-0.1.5.dist-info/RECORD
